nonebot_plugin_abs/__init__.py
nonebot_plugin_abs/data_source.py
nonebot_plugin_abs/emoji.py
nonebot_plugin_abs-1.0.2.dist-info/WHEEL
nonebot_plugin_abs-1.0.2.dist-info/METADATA
nonebot_plugin_abs-1.0.2.dist-info/RECORD
