Metadata-Version: 2.3
Name: nonebot-plugin-abs
Version: 1.0.2
Summary: 插件描述
Author: fllesser
Author-email: fllesser <fllessive@gmail.com>
Requires-Dist: jieba>=0.42.1
Requires-Dist: pinyin>=0.4.0
Requires-Dist: nonebot2>=2.3.0,<3.0.0
Requires-Dist: nonebot-plugin-alconna>=0.59.4,<1.0.0
Requires-Python: >=3.10
Project-URL: Homepage, https://github.com/fllesser/nonebot-plugin-abs
Project-URL: Issues, https://github.com/fllesser/nonebot-plugin-abs/issues
Project-URL: Repository, https://github.com/fllesser/nonebot-plugin-abs.git
